CHANGELOG.md
base16_colorlib/__init__.py
base16_colorlib/color_scheme.py
base16_colorlib/utils.py
base16_colorlib/version.py
base16_colorlib-0.2.0.dist-info/LICENSE
base16_colorlib-0.2.0.dist-info/METADATA
base16_colorlib-0.2.0.dist-info/WHEEL
base16_colorlib-0.2.0.dist-info/RECORD
