Metadata-Version: 2.1
Name: base16-colorlib
Version: 0.2.0
Summary: base16 color schemes for your python projects
Home-page: https://github.com/MOIS3Y/base16-colorlib
License: GPL-3.0-or-later
Keywords: base16,color,colorlib,theme,scheme
Author: MOIS3Y
Author-email: stepan@zhukovsky.me
Requires-Python: >=3.8.1,<4.0.0
Classifier: License :: OSI Approved :: GNU General Public License v3 or later (GPLv3+)
Classifier: Programming Language :: Python :: 3
Classifier: Programming Language :: Python :: 3.9
Classifier: Programming Language :: Python :: 3.10
Classifier: Programming Language :: Python :: 3.11
Project-URL: Repository, https://github.com/MOIS3Y/base16-colorlib
